json_graph_lite/__init__.py
json_graph_lite/common.py
json_graph_lite/edge.py
json_graph_lite/graph.py
json_graph_lite/graphs.py
json_graph_lite/jgf.py
json_graph_lite/node.py
tests/__init__.py
tests/test_graphs.py
tests/test_jgf.py
json_graph_lite-0.8a0.dist-info/LICENSE
json_graph_lite-0.8a0.dist-info/METADATA
json_graph_lite-0.8a0.dist-info/WHEEL
json_graph_lite-0.8a0.dist-info/top_level.txt
json_graph_lite-0.8a0.dist-info/RECORD
