Metadata-Version: 2.1
Name: json-graph-lite
Version: 0.8a0
Summary: Lightweight graph implementation with JSON serialization
Home-page: https://github.com/rnd0101/json-graph-lite
Author: Roman Suzi
Author-email: roman.suzi@gmail.com
License: UNKNOWN
Platform: UNKNOWN
Classifier: Programming Language :: Python :: 2.7
Classifier: Programming Language :: Python :: 3
Classifier: Development Status :: 3 - Alpha
Classifier: License :: OSI Approved :: MIT License
Classifier: Operating System :: OS Independent
Classifier: Topic :: Software Development :: Libraries
